arrowsqlbcpy-0.2.1.data/purelib/arrowsqlbcpy/__init__.py
arrowsqlbcpy-0.2.1.data/purelib/arrowsqlbcpy/py.typed
arrowsqlbcpy-0.2.1.data/purelib/arrowsqlbcpy/lib/ArrowSqlBulkCopyNet.dll
arrowsqlbcpy-0.2.1.data/purelib/arrowsqlbcpy/lib/Microsoft.Data.SqlClient.SNI.dll
arrowsqlbcpy-0.2.1.dist-info/METADATA
arrowsqlbcpy-0.2.1.dist-info/WHEEL
arrowsqlbcpy-0.2.1.dist-info/top_level.txt
arrowsqlbcpy-0.2.1.dist-info/RECORD
