Metadata-Version: 2.2
Name: arrowsqlbcpy
Version: 0.2.1
Summary: A tiny library that uses .Net SqlBulkCopy to enable fast data loading to Microsoft SQL Server. Apache Arrow is used to serialise data between Python and the native DLL. .Net Native Library AOT compilation is used to generate the native DLL.
Author-email: Russel Webber <24542073+RusselWebber@users.noreply.github.com>
License: MIT
Project-URL: Repository, https://github.com/RusselWebber/arrowsqlbcpy.git
Keywords: bcp,sql,pandas
Classifier: Development Status :: 4 - Beta
Classifier: Intended Audience :: Developers
Classifier: Programming Language :: Python :: 3.9
Classifier: Programming Language :: Python :: 3.10
Classifier: Programming Language :: Python :: 3.11
Classifier: Programming Language :: Python :: 3.12
Classifier: Programming Language :: Python :: 3.13
Classifier: Programming Language :: C#
Classifier: Programming Language :: Python :: Implementation :: CPython
Classifier: Topic :: Database
Classifier: Topic :: Database :: Database Engines/Servers
Requires-Python: >=3.9
Requires-Dist: pandas>=2.2.3
Requires-Dist: pyarrow>=19.0.0
